words2links/__init__.py
words2links/server.py
words2links-0.1.2.dist-info/METADATA
words2links-0.1.2.dist-info/WHEEL
words2links-0.1.2.dist-info/entry_points.txt
words2links-0.1.2.dist-info/RECORD
