Metadata-Version: 2.4
Name: words2links
Version: 0.1.2
Summary: 从关键词到中国知网CSSCI论文链接的MCP服务
Requires-Python: >=3.12
Requires-Dist: mcp>=1.6.0
Requires-Dist: playwright>=1.40.0
